{
    "flags": {},
    "imageData": [
        {
            "input": "Ackermann, Rud., Dr. Studienrat, Wilmersdorf, Haiderose | 1",
            "Nachname": "Ackermann",
            "Vorname": "Rud.",
            "Titel": "Dr.",
            "Beruf": "Studienrat",
            "Sozialer Stand": null,
            "Begleitung": null,
            "Wohnort": "Wilmersdorf",
            "Wohnung": "Haiderose",
            "Personenanzahl": "1"
        },
        {
            "input": "Auert, Herm., Dr., Rechtsanwalt, Berlin, St. Hubertus | 1",
            "Nachname": "Auert",
            "Vorname": "Herm.",
            "Titel": "Dr.",
            "Beruf": "Rechtsanwalt",
            "Sozialer Stand": null,
            "Begleitung": null,
            "Wohnort": "Berlin",
            "Wohnung": "St. Hubertus",
            "Personenanzahl": "1"
        },
        {
            "input": "d' Avance, George, Bankier, mit Frau, Berlin, St. Hubertus | 2",
            "Nachname": "d' Avance",
            "Vorname": "George",
            "Titel": null,
            "Beruf": "Bankier",
            "Sozialer Stand": null,
            "Begleitung": "mit Frau",
            "Wohnort": "Berlin",
            "Wohnung": "St. Hubertus",
            "Personenanzahl": "2"
        },
        {
            "input": "Adam, Walter, Berlin, Wikinger Hof | 1",
            "Nachname": "Adam",
            "Vorname": "Walter",
            "Titel": null,
            "Beruf": null,
            "Sozialer Stand": null,
            "Begleitung": null,
            "Wohnort": "Berlin",
            "Wohnung": "Wikinger Hof",
            "Personenanzahl": "1"
        },
        {
            "input": "Alloring, Heinrich, Direktor, mit Frau, Berlin, Central=Hotel | 2",
            "Nachname": "Alloring",
            "Vorname": "Heinrich",
            "Titel": null,
            "Beruf": "Direktor",
            "Sozialer Stand": null,
            "Begleitung": "mit Frau",
            "Wohnort": "Berlin",
            "Wohnung": "Central=Hotel",
            "Personenanzahl": "2"
        },
        {
            "input": "Alt, Richard, Kaufmann, Remscheidt, Preußenhof | 1",
            "Nachname": "Alt",
            "Vorname": "Richard",
            "Titel": null,
            "Beruf": "Kaufmann",
            "Sozialer Stand": null,
            "Begleitung": null,
            "Wohnort": "Remscheidt",
            "Wohnung": "Preußenhof",
            "Personenanzahl": "1"
        },
        {
            "input": "Aue, Walter, Kaufmann, Lübeck, Preußenhof | 1",
            "Nachname": "Aue",
            "Vorname": "Walter",
            "Titel": null,
            "Beruf": "Kaufmann",
            "Sozialer Stand": null,
            "Begleitung": null,
            "Wohnort": "Lübeck",
            "Wohnung": "Preußenhof",
            "Personenanzahl": "1"
        },
        {
            "input": "Abraham, Max, Kaufmann, Nürnberg, Preußenhof | 1",
            "Nachname": "Abraham",
            "Vorname": "Max",
            "Titel": null,
            "Beruf": "Kaufmann",
            "Sozialer Stand": null,
            "Begleitung": null,
            "Wohnort": "Nürnberg",
            "Wohnung": "Preußenhof",
            "Personenanzahl": "1"
        },
        {
            "input": "Abrahamso, Adolf, Kaufmann, Stettin, Central=Hotel | 1",
            "Nachname": "Abrahamso",
            "Vorname": "Adolf",
            "Titel": null,
            "Beruf": "Kaufmann",
            "Sozialer Stand": null,
            "Begleitung": null,
            "Wohnort": "Stettin",
            "Wohnung": "Central=Hotel",
            "Personenanzahl": "1"
        },
        {
            "input": "Adler, Bruno, Berlin, Preußenhof | 1",
            "Nachname": "Adler",
            "Vorname": "Bruno",
            "Titel": null,
            "Beruf": null,
            "Sozialer Stand": null,
            "Begleitung": null,
            "Wohnort": "Berlin",
            "Wohnung": "Preußenhof",
            "Personenanzahl": "1"
        },
        {
            "input": "Angerhausen, W. Ober=Ingenieur, Berlin, Central=Hotel | 1",
            "Nachname": "Angerhausen",
            "Vorname": "W.",
            "Titel": null,
            "Beruf": "Ober=Ingenieur",
            "Sozialer Stand": null,
            "Begleitung": null,
            "Wohnort": "Berlin",
            "Wohnung": "Central=Hotel",
            "Personenanzahl": "1"
        },
        {
            "input": "Buck, Charlotte, Kranken=Schwester, Kansen, Pommernhaus | 1",
            "Nachname": "Buck",
            "Vorname": "Charlotte",
            "Titel": null,
            "Beruf": "Kranken=Schwester",
            "Sozialer Stand": null,
            "Begleitung": null,
            "Wohnort": "Kansen",
            "Wohnung": "Pommernhaus",
            "Personenanzahl": "1"
        },
        {
            "input": "Bluth, Hugo, Pfarrer, mit Frau, Landsberg, Pommernhaus | 2",
            "Nachname": "Bluth",
            "Vorname": "Hugo",
            "Titel": null,
            "Beruf": "Pfarrer",
            "Sozialer Stand": null,
            "Begleitung": "mit Frau",
            "Wohnort": "Landsberg",
            "Wohnung": "Pommernhaus",
            "Personenanzahl": "2"
        },
        {
            "input": "Berger, Luise, Frau, Berlin, Achilles | 1",
            "Nachname": "Berger",
            "Vorname": "Luise",
            "Titel": null,
            "Beruf": null,
            "Sozialer Stand": "Frau",
            "Begleitung": null,
            "Wohnort": "Berlin",
            "Wohnung": "Achilles",
            "Personenanzahl": "1"
        },
        {
            "input": "Bandlow, Ida, Torgelow, Neuestraße 9 | 1",
            "Nachname": "Bandlow",
            "Vorname": "Ida",
            "Titel": null,
            "Beruf": null,
            "Sozialer Stand": null,
            "Begleitung": null,
            "Wohnort": "Torgelow",
            "Wohnung": "Neuestraße 9",
            "Personenanzahl": "1"
        },
        {
            "input": "Behrens, Lina, Witwe, Wolgast, Grünestraße 20 | 1",
            "Nachname": "Behrens",
            "Vorname": "Lina",
            "Titel": null,
            "Beruf": "Witwe",
            "Sozialer Stand": null,
            "Begleitung": null,
            "Wohnort": "Wolgast",
            "Wohnung": "Grünestraße 20",
            "Personenanzahl": "1"
        },
        {
            "input": "Bahlke, Hans, Kaufmann, Stettin, Preußenhof | 1",
            "Nachname": "Bahlke",
            "Vorname": "Hans",
            "Titel": null,
            "Beruf": "Kaufmann",
            "Sozialer Stand": null,
            "Begleitung": null,
            "Wohnort": "Stettin",
            "Wohnung": "Preußenhof",    
            "Personenanzahl": "1"
        },
        {
            "input": "Bergmann, Hans, Kaufmann, Nürnberg, Preußenhof | 1",
            "Nachname": "Bergmann",
            "Vorname": "Hans",
            "Titel": null,
            "Beruf": "Kaufmann",
            "Sozialer Stand": null,
            "Begleitung": null,
            "Wohnort": "Nürnberg",
            "Wohnung": "Preußenhof",
            "Personenanzahl": "1"
        },
        {
            "input": "Bernert, Paul, Berlin, Europäischer Hof | 1",
            "Nachname": "Bernert",
            "Vorname": "Paul",
            "Titel": null,
            "Beruf": null,
            "Sozialer Stand": null,
            "Begleitung": null,
            "Wohnort": "Berlin",
            "Wohnung": "Europäischer Hof",
            "Personenanzahl": "1"
        },
        {
            "input": "Berns, Emil, Direktor, Berlin, Europäischer Hof | 1",
            "Nachname": "Berns",
            "Vorname": "Emil",
            "Titel": null,
            "Beruf": "Direktor",
            "Sozialer Stand": null,
            "Begleitung": null,
            "Wohnort": "Berlin",
            "Wohnung": "Europäischer Hof",
            "Personenanzahl": "1"
        },
        {
            "input": "Bolle, Georg, Kaufmann, Berlin=Hermsdorf, Jeschkes Hotel | 1",
            "Nachname": "Bolle",
            "Vorname": "Georg",
            "Titel": null,
            "Beruf": "Kaufmann",
            "Sozialer Stand": null,
            "Begleitung": null,
            "Wohnort": "Berlin=Hermsdorf",
            "Wohnung": "Jeschkes Hotel",
            "Personenanzahl": "1"
        },
        {
            "input": "Böttcher, Walter, Kaufmann, Neukölln, Wikinger Hof | 1",
            "Nachname": "Böttcher",
            "Vorname": "Walter",
            "Titel": null,
            "Beruf": "Kaufmann",
            "Sozialer Stand": null,
            "Begleitung": null,
            "Wohnort": "Neukölln",
            "Wohnung": "Wikinger Hof",
            "Personenanzahl": "1"
        },
        {
            "input": "Buschmann, Friedrich, Kaufmann, Bielefeld, Preußenhof | 1",
            "Nachname": "Buschmann",
            "Vorname": "Friedrich",
            "Titel": null,
            "Beruf": "Kaufmann",
            "Sozialer Stand": null,
            "Begleitung": null,
            "Wohnort": "Bielefeld",
            "Wohnung": "Preußenhof",
            "Personenanzahl": "1"
        },
        {
            "input": "Bartusch, Frieda, Frau, Stettin, Pommernhaus | 1",
            "Nachname": "Bartusch",
            "Vorname": "Frieda",
            "Titel": null,
            "Beruf": null,
            "Sozialer Stand": "Frau",
            "Begleitung": null,
            "Wohnort": "Stettin",
            "Wohnung": "Pommernhaus",
            "Personenanzahl": "1"
        },
        {
            "input": "Bechler, M., Frau, Slotzenhagen=Kratzwiek, Pommernhaus | 1",
            "Nachname": "Bechler",
            "Vorname": "M.",
            "Titel": null,
            "Beruf": null,
            "Sozialer Stand": "Frau",
            "Begleitung": null,
            "Wohnort": "Slotzenhagen=Kratzwiek",    
            "Wohnung": "Pommernhaus",
            "Personenanzahl": "1"
        },
        {
            "input": "Beversdorf, Erna, Frau, Stettin, Pommernhaus | 1",
            "Nachname": "Beversdorf",
            "Vorname": "Erna",
            "Titel": null,
            "Beruf": null,
            "Sozialer Stand": "Frau",
            "Begleitung": null,
            "Wohnort": "Stettin",
            "Wohnung": "Pommernhaus",
            "Personenanzahl": "1"
        },
        {
            "input": "Buck, Elfriede, Frau, Stolzenhagen, Pommernhaus | 1",
            "Nachname": "Buck",
            "Vorname": "Elfriede",
            "Titel": null,
            "Beruf": null,
            "Sozialer Stand": "Frau",
            "Begleitung": null,
            "Wohnort": "Stolzenhagen",
            "Wohnung": "Pommernhaus",
            "Personenanzahl": "1"
        },
        {
            "input": "Bluhm, Lotte, Frau, Stettin=Grabow, Pommernhaus | 1",
            "Nachname": "Bluhm",
            "Vorname": "Lotte",
            "Titel": null,
            "Beruf": null,
            "Sozialer Stand": "Frau",
            "Begleitung": null,
            "Wohnort": "Stettin=Grabow",
            "Wohnung": "Pommernhaus",
            "Personenanzahl": "1"
        }
],
"imagePath": "groundtruth_text_annotation/1926/swinba_636776093_1926_05_15_00000001/table_0.jpg"
}